meshcore_proxy/__init__.py
meshcore_proxy/cli.py
meshcore_proxy/decoder.py
meshcore_proxy/proxy.py
meshcore_proxy-0.4.0.dist-info/METADATA
meshcore_proxy-0.4.0.dist-info/WHEEL
meshcore_proxy-0.4.0.dist-info/entry_points.txt
meshcore_proxy-0.4.0.dist-info/top_level.txt
meshcore_proxy-0.4.0.dist-info/RECORD
