Metadata-Version: 2.4
Name: meshcore-proxy
Version: 0.4.0
Summary: TCP proxy for MeshCore companion radios
License: MIT
Keywords: meshcore,lora,mesh,radio,proxy
Classifier: Development Status :: 3 - Alpha
Classifier: Intended Audience :: Developers
Classifier: License :: OSI Approved :: MIT License
Classifier: Programming Language :: Python :: 3
Classifier: Programming Language :: Python :: 3.10
Classifier: Programming Language :: Python :: 3.11
Classifier: Programming Language :: Python :: 3.12
Requires-Python: >=3.10
Requires-Dist: meshcore>=2.2.0
Requires-Dist: bleak>=0.21.0
Requires-Dist: pyserial-asyncio-fast>=0.11
Provides-Extra: dev
Requires-Dist: pytest>=7.0; extra == "dev"
Requires-Dist: pytest-asyncio>=0.21; extra == "dev"
Requires-Dist: black; extra == "dev"
Requires-Dist: ruff; extra == "dev"
